lunnaris_pyinject/__init__.py
lunnaris_pyinject/dependency.py
lunnaris_pyinject/injection.py
lunnaris_pyinject-1.0.0.dist-info/METADATA
lunnaris_pyinject-1.0.0.dist-info/WHEEL
lunnaris_pyinject-1.0.0.dist-info/top_level.txt
lunnaris_pyinject-1.0.0.dist-info/RECORD
