Metadata-Version: 2.1
Name: lunnaris-pyinject
Version: 1.0.0
Summary: Dependency injection package
Home-page: https://github.com/KennethUlloa/pyinject
Author: Kenneth Ulloa
Author-email: ulloakenth@gmail.com
Classifier: Intended Audience :: Developers
Classifier: Topic :: Utilities
Requires-Python: >=3.10
Provides-Extra: dev
Requires-Dist: pytest ; extra == 'dev'
